skillforge/__init__.py
skillforge/cli.py
skillforge/analyzers/__init__.py
skillforge/analyzers/intent_analyzer.py
skillforge/analyzers/learning_pipeline.py
skillforge/analyzers/pattern_detector.py
skillforge/analyzers/skill_discovery.py
skillforge/analyzers/skill_optimizer.py
skillforge/analyzers/usage_tracker.py
skillforge/data/scripts/install.sh
skillforge/data/skill_files/CLAUDE.md
skillforge/data/skill_files/SKILL.md
skillforge/data/skill_files/commands/sf/analyze.md
skillforge/data/skill_files/commands/sf/config.md
skillforge/data/skill_files/commands/sf/generate.md
skillforge/data/skill_files/commands/sf/introspect.md
skillforge/data/skill_files/commands/sf/list.md
skillforge/data/skill_files/commands/sf/optimize.md
skillforge/data/skill_files/commands/sf/reset.md
skillforge/data/skill_files/commands/sf/status.md
skillforge/data/skill_files/commands/sf/update.md
skillforge/data/skill_files/commands/sf/wizard.md
skillforge/data/skill_files/core/GENERATOR.md
skillforge/data/skill_files/core/MCP_INTEGRATION.md
skillforge/data/skill_files/core/ORCHESTRATION.md
skillforge/data/skill_files/core/PATTERNS.md
skillforge/data/skill_files/core/RULES.md
skillforge/data/skill_files/core/SKILLFORGE.md
skillforge/data/skill_files/core/VISUAL_OUTPUT.md
skillforge/data/skill_files/core/WORKFLOWS.md
skillforge/data/templates/base-skill.template
skillforge/data/templates/tech-stack/python-api.template
skillforge/data/templates/tech-stack/react-spa.template
skillforge/data/templates/tech-stack/supabase-integration.template
skillforge/data/templates/tech-stack/nextjs-fullstack/SKILL.md.template
skillforge/data/templates/tech-stack/nextjs-fullstack/references/api-routes.md.template
skillforge/data/templates/tech-stack/nextjs-fullstack/references/components.md.template
skillforge/data/templates/tech-stack/nextjs-fullstack/references/data-fetching.md.template
skillforge/data/templates/tech-stack/nextjs-fullstack/references/error-handling.md.template
skillforge-1.2.0.dist-info/licenses/LICENSE
skillforge-1.2.0.dist-info/METADATA
skillforge-1.2.0.dist-info/WHEEL
skillforge-1.2.0.dist-info/entry_points.txt
skillforge-1.2.0.dist-info/top_level.txt
skillforge-1.2.0.dist-info/RECORD
