Metadata-Version: 2.4
Name: skillforge
Version: 1.2.0
Summary: Meta-programming framework for Claude Code skills
Home-page: https://github.com/omarpioselli/SkillForge
Author: Omar Pioselli
Author-email: 
License: MIT
Project-URL: Homepage, https://github.com/omarpioselli/SkillForge
Project-URL: Documentation, https://github.com/omarpioselli/SkillForge/blob/main/docs/
Project-URL: Repository, https://github.com/omarpioselli/SkillForge
Project-URL: Issues, https://github.com/omarpioselli/SkillForge/issues
Keywords: claude-code,skills,meta-programming,ai-development,code-generation
Classifier: Development Status :: 4 - Beta
Classifier: Intended Audience :: Developers
Classifier: Topic :: Software Development :: Code Generators
Classifier: License :: OSI Approved :: MIT License
Classifier: Programming Language :: Python :: 3
Classifier: Programming Language :: Python :: 3.11
Classifier: Programming Language :: Python :: 3.12
Classifier: Programming Language :: Python :: 3.13
Requires-Python: >=3.11
License-File: LICENSE
Requires-Dist: pyyaml>=6.0
Requires-Dist: requests>=2.31.0
Requires-Dist: click>=8.0
Provides-Extra: dev
Requires-Dist: pytest>=7.0; extra == "dev"
Requires-Dist: pytest-cov>=4.0; extra == "dev"
Requires-Dist: black>=23.0; extra == "dev"
Requires-Dist: flake8>=6.0; extra == "dev"
Requires-Dist: mypy>=1.0; extra == "dev"
Provides-Extra: test
Requires-Dist: pytest>=7.0; extra == "test"
Requires-Dist: pytest-cov>=4.0; extra == "test"
Dynamic: home-page
Dynamic: license-file
Dynamic: requires-python
